amodem/__init__.py
amodem/__main__.py
amodem/alsa.py
amodem/async_reader.py
amodem/audio.py
amodem/calib.py
amodem/common.py
amodem/config.py
amodem/detect.py
amodem/dsp.py
amodem/equalizer.py
amodem/framing.py
amodem/levinson.py
amodem/main.py
amodem/recv.py
amodem/sampling.py
amodem/send.py
amodem/stream.py
amodem/tests/__init__.py
amodem/tests/test_alsa.py
amodem/tests/test_async_reader.py
amodem/tests/test_audio.py
amodem/tests/test_calib.py
amodem/tests/test_common.py
amodem/tests/test_configs.py
amodem/tests/test_detect.py
amodem/tests/test_dsp.py
amodem/tests/test_equalizer.py
amodem/tests/test_framing.py
amodem/tests/test_sampling.py
amodem/tests/test_stream.py
amodem/tests/test_transfer.py
amodem/tests/utils.py
amodem-1.16.0.dist-info/LICENSE
amodem-1.16.0.dist-info/METADATA
amodem-1.16.0.dist-info/WHEEL
amodem-1.16.0.dist-info/entry_points.txt
amodem-1.16.0.dist-info/top_level.txt
amodem-1.16.0.dist-info/RECORD
