Metadata-Version: 2.1
Name: amodem
Version: 1.16.0
Summary: Audio Modem Communication Library
Author-email: Roman Zeyde <dev@romanzey.de>
License: MIT
Project-URL: Homepage, https://github.com/romanz/amodem
Project-URL: Issues, https://github.com/romanz/amodem/issues
Classifier: Development Status :: 5 - Production/Stable
Classifier: Intended Audience :: Developers
Classifier: Intended Audience :: Information Technology
Classifier: License :: OSI Approved :: MIT License
Classifier: Operating System :: POSIX
Classifier: Programming Language :: Python :: 3.7
Classifier: Programming Language :: Python :: 3.8
Classifier: Programming Language :: Python :: 3.9
Classifier: Programming Language :: Python :: 3.10
Classifier: Programming Language :: Python :: 3.11
Classifier: Programming Language :: Python :: 3.12
Classifier: Programming Language :: Python :: 3.13
Classifier: Topic :: Software Development :: Libraries :: Python Modules
Classifier: Topic :: System :: Networking
Classifier: Topic :: Communications
Requires-Python: >=3.7
License-File: LICENSE
Requires-Dist: numpy
